botsniffer/__init__.py
botsniffer/scanner.py
botsniffer/data/botcode.pkl
botsniffer/data/pep8-style.txt
botsniffer/feature_extraction/__init__.py
botsniffer/feature_extraction/comments.py
botsniffer/feature_extraction/complexity.py
botsniffer/feature_extraction/feature_extraction.py
botsniffer/feature_extraction/indentation.py
botsniffer/feature_extraction/patterns.py
botsniffer/feature_extraction/style_guide.py
botsniffer/ml_model/__init__.py
botsniffer/ml_model/model.py
botsniffer-0.1.dist-info/LICENSE
botsniffer-0.1.dist-info/METADATA
botsniffer-0.1.dist-info/WHEEL
botsniffer-0.1.dist-info/entry_points.txt
botsniffer-0.1.dist-info/top_level.txt
botsniffer-0.1.dist-info/RECORD
