Metadata-Version: 2.1
Name: botsniffer
Version: 0.1
Summary: Detects AI generated code using ML
Home-page: https://github.com/oscarvalenzuelab/botsniffer
Author: Oscar Valenzuela B.
Author-email: alkamod@gmail.com
License: Apache-2.0
Classifier: Programming Language :: Python :: 3
Classifier: Operating System :: POSIX :: Linux
Classifier: Development Status :: 3 - Alpha
Classifier: License :: OSI Approved :: Apache Software License
License-File: LICENSE
Requires-Dist: sklearn
Requires-Dist: numpy
Requires-Dist: pandas
Requires-Dist: radon
